xmipptomo/__init__.py
xmipptomo/bibtex.py
xmipptomo/protocols.conf
xmipptomo/utils.py
xmipptomo/wizards.py
xmipptomo/xmipp_logo.png
xmipptomo/convert/__init__.py
xmipptomo/convert/convert.py
xmipptomo/protocols/__init__.py
xmipptomo/protocols/protocol_align_transform.py
xmipptomo/protocols/protocol_applyAlignmentTS.py
xmipptomo/protocols/protocol_apply_alignment_subtomo.py
xmipptomo/protocols/protocol_apply_segmentation.py
xmipptomo/protocols/protocol_cltomo.py
xmipptomo/protocols/protocol_connected_components.py
xmipptomo/protocols/protocol_coords_roi.py
xmipptomo/protocols/protocol_crop_resize_base.py
xmipptomo/protocols/protocol_crop_tomograms.py
xmipptomo/protocols/protocol_deep_misalignment_detection.py
xmipptomo/protocols/protocol_dose_filter.py
xmipptomo/protocols/protocol_extract_subtomos.py
xmipptomo/protocols/protocol_filter_coordinates_by_map.py
xmipptomo/protocols/protocol_flexalign.py
xmipptomo/protocols/protocol_half_maps_subtomos.py
xmipptomo/protocols/protocol_peak_high_contrast.py
xmipptomo/protocols/protocol_phantom_subtomo.py
xmipptomo/protocols/protocol_phantom_tomo.py
xmipptomo/protocols/protocol_project_subtomograms.py
xmipptomo/protocols/protocol_project_top.py
xmipptomo/protocols/protocol_reconstruct_tomograms.py
xmipptomo/protocols/protocol_resizeTS.py
xmipptomo/protocols/protocol_resize_tomograms.py
xmipptomo/protocols/protocol_resolution_local_monotomo.py
xmipptomo/protocols/protocol_roiIJ.py
xmipptomo/protocols/protocol_score_coordinates.py
xmipptomo/protocols/protocol_segment_morphology.py
xmipptomo/protocols/protocol_splitTS.py
xmipptomo/protocols/protocol_subtomo_map_back.py
xmipptomo/protocols/protocol_subtraction_subtomo.py
xmipptomo/tests/__init__.py
xmipptomo/tests/test_protocol_apply_transform.py
xmipptomo/tests/test_protocol_cc_to_roi.py
xmipptomo/tests/test_protocol_cltomo.py
xmipptomo/tests/test_protocol_conected_components.py
xmipptomo/tests/test_protocol_crop.py
xmipptomo/tests/test_protocol_deep_misalignment_detection.py
scipion_em_xmipptomo-3.24.6.2.dist-info/LICENSE
scipion_em_xmipptomo-3.24.6.2.dist-info/METADATA
scipion_em_xmipptomo-3.24.6.2.dist-info/WHEEL
scipion_em_xmipptomo-3.24.6.2.dist-info/entry_points.txt
scipion_em_xmipptomo-3.24.6.2.dist-info/top_level.txt
scipion_em_xmipptomo-3.24.6.2.dist-info/RECORD
