Metadata-Version: 2.1
Name: scipion-em-xmipptomo
Version: 3.24.6.2
Summary: Scipion plugin to deal with xmipp tomography protocols.
Home-page: https://github.com/i2pc/scipion-em-xmipptomo
Author: I2PC
Author-email: scipion@cnb.csic.es
License: UNKNOWN
Keywords: scipion cryoem imageprocessing tomography scipion-3.0
Platform: UNKNOWN
Requires-Dist: scipion-em-xmipp
Requires-Dist: scipion-em-tomo
Requires-Dist: scipion-em>=3.0.8
Requires-Dist: scipion-em-xmippBase
